cs2api/__init__.py
cs2api/api.py
cs2api-0.1.3.dist-info/licenses/LICENSE
cs2api-0.1.3.dist-info/METADATA
cs2api-0.1.3.dist-info/WHEEL
cs2api-0.1.3.dist-info/top_level.txt
cs2api-0.1.3.dist-info/RECORD
