Metadata-Version: 2.4
Name: cs2api
Version: 0.1.3
Summary: Python API wrapper for Counter-Strike 2 professional match data via BO3.gg
Home-page: https://github.com/tommhe14/cs2api
Author: tommhe14
Author-email: theckley@yahoo.co.uk
License: MIT
Project-URL: Bug Reports, https://github.com/tommhe14/cs2api/issues
Project-URL: Source, https://github.com/tommhe14/cs2api
Keywords: cs2 counter-strike esports api wrapper
Classifier: Development Status :: 3 - Alpha
Classifier: Intended Audience :: Developers
Classifier: License :: OSI Approved :: MIT License
Classifier: Programming Language :: Python :: 3.8
Classifier: Programming Language :: Python :: 3.9
Classifier: Programming Language :: Python :: 3.10
Classifier: Programming Language :: Python :: 3.11
Classifier: Topic :: Software Development :: Libraries :: Python Modules
Requires-Python: >=3.8
License-File: LICENSE
Requires-Dist: aiohttp>=3.8.0
Dynamic: author
Dynamic: author-email
Dynamic: classifier
Dynamic: description
Dynamic: description-content-type
Dynamic: home-page
Dynamic: keywords
Dynamic: license
Dynamic: license-file
Dynamic: project-url
Dynamic: requires-dist
Dynamic: requires-python
Dynamic: summary
